src/LinearSubdivisionFilter.py
src/compute_min_scale.py
src/obj_to_vtk.py
src/post_process.py
src/predict.py
src/saxi.py
src/saxi_dataset.py
src/saxi_eval.py
src/saxi_eval_agg.py
src/saxi_folds.py
src/saxi_gradcam.py
src/saxi_logger.py
src/saxi_nets.py
src/saxi_predict.py
src/saxi_train.py
src/saxi_transforms.py
src/split_train_eval.py
src/utils.py
src/Resources/__init__.py
src/shapeaxi/__about__.py
src/shapeaxi/__init__.py
shapeaxiflo-0.0.4.dist-info/METADATA
shapeaxiflo-0.0.4.dist-info/WHEEL
shapeaxiflo-0.0.4.dist-info/entry_points.txt
shapeaxiflo-0.0.4.dist-info/licenses/LICENSE
shapeaxiflo-0.0.4.dist-info/RECORD
