Metadata-Version: 2.1
Name: shapeaxiflo
Version: 0.0.4
Summary: Shape Analysis Exploration and Interpretability
Project-URL: Source Code, https://github.com/DCBIA-OrthoLab/ShapeAXI/
Author-email: juanprietob <juanprietob@gmail.com>, FlorianDAVAUX <florian.davaux@cpe.fr>
License-Expression: MIT
License-File: LICENSE
Keywords: Shape Analysis
Classifier: Development Status :: 4 - Beta
Classifier: Environment :: GPU :: NVIDIA CUDA :: 11.7
Classifier: Programming Language :: Python
Classifier: Programming Language :: Python :: 3.8
Classifier: Programming Language :: Python :: 3.9
Classifier: Programming Language :: Python :: Implementation :: CPython
Classifier: Programming Language :: Python :: Implementation :: PyPy
Requires-Python: >=3.8
Requires-Dist: frozenlist==1.3.3
Requires-Dist: fsspec==2022.11.0
Requires-Dist: future==0.18.3
Requires-Dist: fvcore==0.1.5.post20221221
Requires-Dist: google-auth-oauthlib==0.4.6
Requires-Dist: google-auth==2.15.0
Requires-Dist: grad-cam==1.4.6
Requires-Dist: grpcio==1.51.1
Requires-Dist: idna==3.4
Requires-Dist: imageio==2.24.0
Requires-Dist: importlib-metadata==6.8.0
Requires-Dist: importlib-resources==6.0.1
Requires-Dist: iopath==0.1.10
Requires-Dist: itk-core==5.3.0
Requires-Dist: itk-filtering==5.3.0
Requires-Dist: itk-io==5.3.0
Requires-Dist: itk-numerics==5.3.0
Requires-Dist: itk-registration==5.3.0
Requires-Dist: itk-segmentation==5.3.0
Requires-Dist: itk==5.3.0
Requires-Dist: jinja2==3.1.2
Requires-Dist: joblib==1.2.0
Requires-Dist: kaleido==0.2.1
Requires-Dist: kiwisolver==1.4.4
Requires-Dist: lightning-bolts==0.7.0
Requires-Dist: lightning-utilities==0.7.0
Requires-Dist: lit==16.0.6
Requires-Dist: mako==1.2.4
Requires-Dist: markdown==3.4.1
Requires-Dist: markupsafe==2.1.1
Requires-Dist: matplotlib==3.7.1
Requires-Dist: medcam==0.1.21
Requires-Dist: monai==1.2.0
Requires-Dist: mpmath==1.3.0
Requires-Dist: multidict==6.0.4
Requires-Dist: networkx==3.0
Requires-Dist: nibabel==5.0.0
Requires-Dist: nptyping==2.4.1
Requires-Dist: numpy==1.25.2
Requires-Dist: oauthlib==3.2.2
Requires-Dist: opencv-python==4.7.0.68
Requires-Dist: packaging==23.0
Requires-Dist: pandas==1.5.2
Requires-Dist: pillow==9.4.0
Requires-Dist: plotly==5.14.1
Requires-Dist: portalocker==2.6.0
Requires-Dist: protobuf==3.20.1
Requires-Dist: pyarrow==12.0.0
Requires-Dist: pyasn1-modules==0.2.8
Requires-Dist: pyasn1==0.4.8
Requires-Dist: pycodestyle==2.10.0
Requires-Dist: pyensae==1.3.967
Requires-Dist: pynrrd==1.0.0
Requires-Dist: pyparsing==3.0.9
Requires-Dist: pyquickhelper==1.12.3806
Requires-Dist: pyquicksetup==0.2.4
Requires-Dist: python-dateutil==2.8.2
Requires-Dist: pytorch-lightning==1.8.6
Requires-Dist: pytz==2022.7
Requires-Dist: pywavelets==1.4.1
Requires-Dist: pyyaml==6.0
Requires-Dist: requests-oauthlib==1.3.1
Requires-Dist: requests==2.28.1
Requires-Dist: rsa==4.9
Requires-Dist: scikit-image==0.19.3
Requires-Dist: scikit-learn==1.2.0
Requires-Dist: scipy==1.9.3
Requires-Dist: seaborn==0.13.0
Requires-Dist: simpleitk==2.2.1
Requires-Dist: six==1.16.0
Requires-Dist: sympy==1.12
Requires-Dist: tabulate==0.9.0
Requires-Dist: tenacity==8.2.2
Requires-Dist: tensorboard-data-server==0.6.1
Requires-Dist: tensorboard-plugin-wit==1.8.1
Requires-Dist: tensorboard==2.11.0
Requires-Dist: tensorboardx==2.5.1
Requires-Dist: termcolor==2.1.1
Requires-Dist: threadpoolctl==3.1.0
Requires-Dist: tifffile==2022.10.10
Requires-Dist: tomli==2.0.1
Requires-Dist: torch==2.0.1
Requires-Dist: torchaudio==2.0.2
Requires-Dist: torchmetrics==0.11.4
Requires-Dist: torchvision==0.15.2
Requires-Dist: tqdm==4.64.1
Requires-Dist: triton==2.0.0
Requires-Dist: ttach==0.0.3
Requires-Dist: typing-extensions==4.7.0
Requires-Dist: urllib3==1.26.13
Requires-Dist: vtk==9.2.6
Requires-Dist: werkzeug==2.2.2
Requires-Dist: yacs==0.1.8
Requires-Dist: yarl==1.8.2
Requires-Dist: zipp==3.16.2
